<?xml version="1.0" encoding="UTF-8"?>
<LanguageData>
  
  <!-- EN: Stone -->
  <Node_1760558136728_1325.label>岩</Node_1760558136728_1325.label>
  
  <!-- EN: Insect -->
  <Node_1760558136728_1351.label>虫</Node_1760558136728_1351.label>
  
  <!-- EN: Mist -->
  <Node_1760558136728_2908.label>霞</Node_1760558136728_2908.label>
  
  <!-- EN: Sound -->
  <Node_1760558136728_3354.label>音</Node_1760558136728_3354.label>
  
  <!-- EN: Kinoto -->
  <Node_1760558136728_3686.label>乙</Node_1760558136728_3686.label>
  
  <!-- EN: Kanoto -->
  <Node_1760558136728_3758.label>辛</Node_1760558136728_3758.label>
  
  <!-- EN: Mizunoto -->
  <Node_1760558136728_3984.label>癸</Node_1760558136728_3984.label>
  
  <!-- EN: Moon -->
  <Node_1760558136728_4015.label>月</Node_1760558136728_4015.label>
  
  <!-- EN: Tsuchinoto -->
  <Node_1760558136728_4028.label>己</Node_1760558136728_4028.label>
  
  <!-- EN: Thunder -->
  <Node_1760558136728_407.label>雷</Node_1760558136728_407.label>
  
  <!-- EN: Frost -->
  <Node_1760558136728_4447.label>霜</Node_1760558136728_4447.label>
  
  <!-- EN: Kinoe -->
  <Node_1760558136728_4654.label>甲</Node_1760558136728_4654.label>
  
  <!-- EN: Kanoe -->
  <Node_1760558136728_4796.label>庚</Node_1760558136728_4796.label>
  
  <!-- EN: Love -->
  <Node_1760558136728_4980.label>恋</Node_1760558136728_4980.label>
  
  <!-- EN: Mizunoe -->
  <Node_1760558136728_5712.label>壬</Node_1760558136728_5712.label>
  
  <!-- EN: Serpent -->
  <Node_1760558136728_6003.label>蛇</Node_1760558136728_6003.label>
  
  <!-- EN: Flower -->
  <Node_1760558136728_6480.label>花</Node_1760558136728_6480.label>
  
  <!-- EN: Flame -->
  <Node_1760558136728_762.label>炎</Node_1760558136728_762.label>
  
  <!-- EN: Hinoto -->
  <Node_1760558136728_7933.label>丁</Node_1760558136728_7933.label>
  
  <!-- EN: Forest -->
  <Node_1760558136728_7998.label>森</Node_1760558136728_7998.label>
  
  <!-- EN: Sun -->
  <Node_1760558136728_8009.label>日</Node_1760558136728_8009.label>
  
  <!-- EN: Wind -->
  <Node_1760558136728_8155.label>风</Node_1760558136728_8155.label>
  
  <!-- EN: Hinoe -->
  <Node_1760558136728_8240.label>丙</Node_1760558136728_8240.label>
  
  <!-- EN: Water -->
  <Node_1760558136728_8666.label>水</Node_1760558136728_8666.label>
  
  <!-- EN: Tsuchinoe -->
  <Node_1760558136728_8934.label>戊</Node_1760558136728_8934.label>
  
  <!-- EN: Beast -->
  <Node_1760558136728_9234.label>兽</Node_1760558136728_9234.label>
  
</LanguageData>