<?xml version="1.0" encoding="UTF-8"?>
<LanguageData>
  
  <!-- EN: Training rock -->
  <AnimeArsenal_FinalSelectionRock.label>训练用岩石</AnimeArsenal_FinalSelectionRock.label>
  <!-- EN: A training rock that trigger the quest to become a slayer. -->
  <AnimeArsenal_FinalSelectionRock.description>用于触发成为鬼杀队士任务的训练用岩石。</AnimeArsenal_FinalSelectionRock.description>
  <!-- EN: Cannot start the Final Selection at this time. You need at least 3 free colonists. -->
  <AnimeArsenal_FinalSelectionRock.comps.CompUseEffect_StartQuest.failMessage>现在无法开始最终选拔。至少需要三名可行动的殖民者。</AnimeArsenal_FinalSelectionRock.comps.CompUseEffect_StartQuest.failMessage>
  <!-- EN: {0} has summoned a Demon Slayer Corps guide. The Final Selection begins! -->
  <AnimeArsenal_FinalSelectionRock.comps.CompUseEffect_StartQuest.successMessage>{0}召唤了鬼杀队引路人，最终选拔开始了！</AnimeArsenal_FinalSelectionRock.comps.CompUseEffect_StartQuest.successMessage>
  <!-- EN: Initiate Final Selection -->
  <AnimeArsenal_FinalSelectionRock.comps.CompUsable.useLabel>初始化最终选拔</AnimeArsenal_FinalSelectionRock.comps.CompUsable.useLabel>
  
  <!-- EN: final selection rock -->
  <AnimeArsenal_FinalSelectionRocktwo.label>最终选拔岩石</AnimeArsenal_FinalSelectionRocktwo.label>
  <!-- EN: A rock. -->
  <AnimeArsenal_FinalSelectionRocktwo.description>岩石。</AnimeArsenal_FinalSelectionRocktwo.description>
  <!-- EN: Cannot start the Final Selection at this time. You need at least 3 free colonists. -->
  <AnimeArsenal_FinalSelectionRocktwo.comps.CompUseEffect_StartQuest.failMessage>现在无法开始最终选拔。至少需要三名可行动的殖民者。</AnimeArsenal_FinalSelectionRocktwo.comps.CompUseEffect_StartQuest.failMessage>
  <!-- EN: {0} has summoned a Demon Slayer Corps guide. The Final Selection begins! -->
  <AnimeArsenal_FinalSelectionRocktwo.comps.CompUseEffect_StartQuest.successMessage>{0}召唤了鬼杀队引路人，最终选拔开始了！</AnimeArsenal_FinalSelectionRocktwo.comps.CompUseEffect_StartQuest.successMessage>
  <!-- EN: Initiate Final Selection -->
  <AnimeArsenal_FinalSelectionRocktwo.comps.CompUsable.useLabel>初始化最终选拔</AnimeArsenal_FinalSelectionRocktwo.comps.CompUsable.useLabel>
  
</LanguageData>