<?xml version="1.0" encoding="utf-8"?>
<Defs>
  
  <AnimeArsenal.EnchantDef>
    <defName>Sonic_Blade_Technique</defName>
    <label>Sonic Blade Technique</label>
    <description>A technique that allows a Sound Breathing user to imbue their attacks with sonic vibrations.</description>
    <enchantHediff>Sonic_Heart</enchantHediff>
    <resourceGene>Gene_SoundBreath</resourceGene>
    <ticksBetweenCost>450</ticksBetweenCost>
    <resourceCostPerTick>5</resourceCostPerTick>
  </AnimeArsenal.EnchantDef>
  
  <AnimeArsenal.EnchantDef>
    <defName>Sonic_Blade_Technique_Enhanced</defName>
    <label>Enhanced Sonic Blade</label>
    <description>An improved technique with stronger sonic resonance and better efficiency.</description>
    <enchantHediff>Sonic_Heart_Enhanced</enchantHediff>
    <resourceGene>Gene_SoundBreath</resourceGene>
    <ticksBetweenCost>400</ticksBetweenCost>
    <resourceCostPerTick>5</resourceCostPerTick>
  </AnimeArsenal.EnchantDef>
  
  <AnimeArsenal.EnchantDef>
    <defName>Sonic_Blade_Technique_Superior</defName>
    <label>Superior Sonic Blade</label>
    <description>A superior technique with powerful harmonic frequencies and high efficiency.</description>
    <enchantHediff>Sonic_Heart_Superior</enchantHediff>
    <resourceGene>Gene_SoundBreath</resourceGene>
    <ticksBetweenCost>350</ticksBetweenCost>
    <resourceCostPerTick>4</resourceCostPerTick>
  </AnimeArsenal.EnchantDef>
  
  <AnimeArsenal.EnchantDef>
    <defName>Sonic_Blade_Technique_Master</defName>
    <label>Master Sonic Blade</label>
    <description>The ultimate technique with devastating sonic vibrations and maximum efficiency.</description>
    <enchantHediff>Sonic_Heart_Master</enchantHediff>
    <resourceGene>Gene_SoundBreath</resourceGene>
    <ticksBetweenCost>300</ticksBetweenCost>
    <resourceCostPerTick>3</resourceCostPerTick>
  </AnimeArsenal.EnchantDef>
</Defs>
