<?xml version="1.0" encoding="utf-8" ?>
<Defs>
  <AbilityDef>
    <defName>AA_ForwardDash</defName>
    <label>forward dash</label>
    <category>SlayerCorp_Ability_Catergory</category>
    <groupDef>SlayerCorp_DashForward_Group</groupDef>
    <description>Quickly dash forward toward the target to close the distance.</description>
    <iconPath>UI/Icons/ComingSoon</iconPath>
    <cooldownTicksRange>1800</cooldownTicksRange>
    <aiCanUse>true</aiCanUse>
    <displayGizmoWhileUndrafted>false</displayGizmoWhileUndrafted>
    <targetRequired>true</targetRequired>
    <verbProperties>
      <verbClass>Verb_CastAbility</verbClass>
      <range>30</range>
      <warmupTime>0.5</warmupTime>
      <targetParams>
        <canTargetLocations>true</canTargetLocations>
        <canTargetPawns>true</canTargetPawns>
        <canTargetBuildings>false</canTargetBuildings>
      </targetParams>
    </verbProperties>
    <comps>
      <li Class="AnimeArsenal.CompProperties_AbilityForwardDash">
        <minDashDistance>8</minDashDistance>
        <maxDashDistance>15</maxDashDistance>
        <avoidEnemies>false</avoidEnemies>
        <enemyAvoidanceRadius>5</enemyAvoidanceRadius>
        <numberOfDashes>2</numberOfDashes>
        <allowRandomDirection>false</allowRandomDirection>
        <maintainMinDistanceFromTarget>false</maintainMinDistanceFromTarget>
        <minDistanceFromTarget>2</minDistanceFromTarget>
        <castEffecter>AnimeArsenal_BeastJump</castEffecter>
        <landEffecter>AnimeArsenal_DashBack</landEffecter>
        <retryEffecter>AnimeArsenal_DashBack</retryEffecter>
        <grantTemporaryImmunity>false</grantTemporaryImmunity>
        <grantSpeedBoost>false</grantSpeedBoost>
        <grantMoodBoost>false</grantMoodBoost>
        <restoreStamina>false</restoreStamina>
      </li>
    </comps>
  </AbilityDef>
</Defs>
