<?xml version="1.0" encoding="UTF-8"?>
<LanguageData>
  
  <!-- EN: Stone Breathing: Disperse -->
  <Stone_Breathing_Disperse.label>岩之呼吸・散</Stone_Breathing_Disperse.label>
  <!-- EN: A technique that creates cutting attacks around a targeted enemy. -->
  <Stone_Breathing_Disperse.description>在敵方周圍創造斬擊的技法。</Stone_Breathing_Disperse.description>
  <!-- EN: A technique that creates cutting attacks around a targeted enemy. -->
  <Stone_Breathing_Disperse.levels.0.description>在敵方周圍創造斬擊的技法。</Stone_Breathing_Disperse.levels.0.description>
  <!-- EN:  (Level 1) -->
  <Stone_Breathing_Disperse.levels.0.labelSuffix>壹級</Stone_Breathing_Disperse.levels.0.labelSuffix>
  <!-- EN: A technique that creates cutting attacks around a targeted enemy. -->
  <Stone_Breathing_Disperse.levels.1.description>在敵方周圍創造斬擊的技法。</Stone_Breathing_Disperse.levels.1.description>
  <!-- EN:  (Level 2) -->
  <Stone_Breathing_Disperse.levels.1.labelSuffix>貳級</Stone_Breathing_Disperse.levels.1.labelSuffix>
  <!-- EN: A technique that creates cutting attacks around a targeted enemy. -->
  <Stone_Breathing_Disperse.levels.2.description>在敵方周圍創造斬擊的技法。</Stone_Breathing_Disperse.levels.2.description>
  <!-- EN:  (Level 3) -->
  <Stone_Breathing_Disperse.levels.2.labelSuffix>參級</Stone_Breathing_Disperse.levels.2.labelSuffix>
  <!-- EN: A technique that creates cutting attacks around a targeted enemy. -->
  <Stone_Breathing_Disperse.levels.3.description>在敵方周圍創造斬擊的技法。</Stone_Breathing_Disperse.levels.3.description>
  <!-- EN:  (Level 4) -->
  <Stone_Breathing_Disperse.levels.3.labelSuffix>肆級</Stone_Breathing_Disperse.levels.3.labelSuffix>
  <!-- EN: A technique that creates cutting attacks around a targeted enemy. -->
  <Stone_Breathing_Disperse.levels.4.description>在敵方周圍創造斬擊的技法。</Stone_Breathing_Disperse.levels.4.description>
  <!-- EN:  (Level 5) -->
  <Stone_Breathing_Disperse.levels.4.labelSuffix>伍級</Stone_Breathing_Disperse.levels.4.labelSuffix>
  <!-- EN: A technique that creates cutting attacks around a targeted enemy. -->
  <Stone_Breathing_Disperse.levels.5.description>在敵方周圍創造斬擊的技法。</Stone_Breathing_Disperse.levels.5.description>
  <!-- EN:  (Level 6) -->
  <Stone_Breathing_Disperse.levels.5.labelSuffix>陸級</Stone_Breathing_Disperse.levels.5.labelSuffix>
  
</LanguageData>